{
  "title": "משרד בוטיק לדיני משפחה עם ליווי אישי ומדויק",
  "description": "האתר החדש בנוי סביב הערך המרכזי שכבר קיים במותג: שירות אישי, מקצועי ודיסקרטי, עם מעורבות ישירה בכל תיק.",
  "paragraphs": [
    "עו\"ד אליזבט ברזאני דדון, חברת לשכת עורכי הדין בישראל משנת 2008, מלווה לקוחות במצבים אישיים ורגישים הדורשים שילוב בין רגישות אנושית, ניסיון והבנה משפטית מעמיקה.",
    "המשרד מעניק שירות ישיר ואישי, ללא העברת הטיפול למתמחים או לסטודנטים, ומתמקד בבניית מענה משפטי מותאם לנסיבות הייחודיות של כל לקוח ולקוחה."
  ],
  "values": [
    {
      "title": "ניסיון ויציבות",
      "text": "ליווי וייצוג במאות תיקים בדיני משפחה, גירושין, צוואות וירושות."
    },
    {
      "title": "שירות אישי באמת",
      "text": "טיפול ישיר בכל תיק, הקשבה לצרכים הייחודיים של הלקוח והובלה מדויקת של התהליך."
    },
    {
      "title": "דיסקרטיות ורגישות",
      "text": "הבנה שמדובר בנושאים רגישים במיוחד, ולכן העבודה נעשית בכבוד, באחריות ובשקיפות."
    }
  ]
}
